{"41970": "Ancestral Bond", "54307": "Acrobatics", "42178": "Point Blank", "14914": "Phase Acrobatics", "22088": "Elemental Overload", "40907": "Unwavering Stance", "10808": "Vaal Pact", "18663": "Minion Instability", "24426": "Ghost Reaver", "23407": "Perfect Agony", "39085": "Elemental Equilibrium", "54922": "Arrow Dancing", "56075": "Eldritch Battery", "12926": "Iron Grip", "23540": "Conduit", "45175": "Necromantic Aegis", "10661": "Iron Reflexes", "44941": "Avatar of Fire", "31703": "Pain Attunement", "31961": "Resolute Technique", "11455": "Chaos Inoculation", "57279": "Blood Magic", "34098": "Mind Over Matter", "63425": "Zealot's Oath", "17818": "Crimson Dance"}